ignis/__init__.py
ignis/agents.py
ignis/callbacks.py
ignis/datasets.py
ignis/loaders.py
ignis/memories.py
ignis/supervised.py
ignis-0.0.10.dist-info/LICENSE
ignis-0.0.10.dist-info/METADATA
ignis-0.0.10.dist-info/WHEEL
ignis-0.0.10.dist-info/top_level.txt
ignis-0.0.10.dist-info/RECORD
