Metadata-Version: 2.1
Name: ignis
Version: 0.0.10
Summary: Intuitive library for training neural nets in PyTorch
Home-page: https://github.com/Catastropha/ignis
Author: Teodor Scorpan
Author-email: teodor.scorpan@gmail.com
License: UNKNOWN
Platform: UNKNOWN
Classifier: Programming Language :: Python :: 3.6
Classifier: License :: OSI Approved :: MIT License
Classifier: Operating System :: OS Independent
